cse/__init__.py
cse/cse.py
cse.py-1.1.3.dist-info/LICENSE
cse.py-1.1.3.dist-info/METADATA
cse.py-1.1.3.dist-info/WHEEL
cse.py-1.1.3.dist-info/top_level.txt
cse.py-1.1.3.dist-info/RECORD
