Metadata-Version: 2.1
Name: cse.py
Version: 1.1.3
Summary: An asynchronous Google Search Engine API wrapper
Home-page: https://github.com/Hype3808/cse.py
Author: Hype3808
License: MIT
Keywords: google-api-wrapper,google,chrome-search-engine,cse
Platform: UNKNOWN
Classifier: Development Status :: 3 - Alpha
Classifier: Intended Audience :: Developers
Classifier: License :: OSI Approved :: MIT License
Classifier: Programming Language :: Python :: 3
License-File: LICENSE
Requires-Dist: aiohttp
